fullksuid/Id.py
fullksuid/Instance.py
fullksuid/Schemes.py
fullksuid/__init__.py
fullksuid/generator.py
fullksuid/validation.py
fullksuid-1.2.2.dist-info/LICENSE
fullksuid-1.2.2.dist-info/METADATA
fullksuid-1.2.2.dist-info/WHEEL
fullksuid-1.2.2.dist-info/top_level.txt
fullksuid-1.2.2.dist-info/RECORD
